scphylo/__init__.py
scphylo/external/_mp3.py
scphylo/external/_mltd.cpp
scphylo/external/_mltd.cpython-312-i386-linux-musl.so
scphylo/external/_betabinom.py
scphylo/external/_scprob.pyx
scphylo/external/_scistree.pyx
scphylo/external/_scprob.cpython-312-i386-linux-musl.so
scphylo/external/_scistree.cpython-312-i386-linux-musl.so
scphylo/external/_scistree.cpp
scphylo/external/_scite.pyx
scphylo/external/_mltd.pyx
scphylo/external/_scite.cpp
scphylo/external/__init__.py
scphylo/external/_scite.cpython-312-i386-linux-musl.so
scphylo/external/_scprob.cpp
scphylo/external/gpps/_nh2lgf.py
scphylo/external/gpps/_gpps_hc.py
scphylo/external/gpps/_utils_ilp.py
scphylo/external/gpps/_gpps_ilp.py
scphylo/external/gpps/_utils_hc.py
scphylo/external/gpps/__init__.py
scphylo/external/mltd/mltd.h
scphylo/external/mltd/mltd.cpp
scphylo/external/scite/mcmcBinTreeMove.cpp
scphylo/external/scite/output.h
scphylo/external/scite/treelist.h
scphylo/external/scite/findBestTrees.cpp
scphylo/external/scite/rand.cpp
scphylo/external/scite/scoreBinTree.cpp
scphylo/external/scite/trees.cpp
scphylo/external/scite/matrices.h
scphylo/external/scite/mcmcTreeMove.cpp
scphylo/external/scite/scoreBinTree.h
scphylo/external/scite/scoreTree.h
scphylo/external/scite/output.cpp
scphylo/external/scite/mcmcTreeMove.h
scphylo/external/scite/matrices.cpp
scphylo/external/scite/trees.h
scphylo/external/scite/mcmc.cpp
scphylo/external/scite/mcmcBinTreeMove.h
scphylo/external/scite/rand.h
scphylo/external/scite/findBestTrees.h
scphylo/external/scite/treelist.cpp
scphylo/external/scite/mcmc.h
scphylo/external/scite/scoreTree.cpp
scphylo/external/scprob/main.h
scphylo/external/scprob/main.cpp
scphylo/external/scistree/Utils.cpp
scphylo/external/scistree/PhylogenyTreeBasic.h
scphylo/external/scistree/UtilsNumerical.h
scphylo/external/scistree/ctpl_stl.h
scphylo/external/scistree/BinaryMatrix.cpp
scphylo/external/scistree/UnWeightedGraph.h
scphylo_tools-0.0.5.dist-info/WHEEL
scphylo_tools-0.0.5.dist-info/entry_points.txt
scphylo_tools-0.0.5.dist-info/top_level.txt
scphylo_tools-0.0.5.dist-info/METADATA
scphylo_tools-0.0.5.dist-info/RECORD
scphylo_tools-0.0.5.dist-info/licenses/LICENSE.md
