Metadata-Version: 2.4
Name: scphylo-tools
Version: 0.0.5
Summary: A python toolkit for single-cell tumor phylogenetic analysis
Author-email: Farid Rashidi <farid.rsh@gmail.com>
Maintainer-email: Farid Rashidi <farid.rsh@gmail.com>
License: BSD-3-Clause
Project-URL: Homepage, https://github.com/faridrashidi/scphylo-tools
Project-URL: Documentation, https://scphylo-tools.readthedocs.io/en/latest
Project-URL: Source Code, https://github.com/faridrashidi/scphylo-tools
Project-URL: Download, https://github.com/faridrashidi/scphylo-tools
Keywords: tumor phylogeny,single cell,tools
Classifier: Development Status :: 5 - Production/Stable
Classifier: Intended Audience :: Developers
Classifier: Intended Audience :: Science/Research
Classifier: Natural Language :: English
Classifier: Framework :: Jupyter
Classifier: Operating System :: MacOS :: MacOS X
Classifier: Operating System :: Microsoft :: Windows
Classifier: Operating System :: POSIX :: Linux
Classifier: Programming Language :: Python :: 3
Classifier: Programming Language :: Python :: 3.11
Classifier: Programming Language :: Python :: 3.12
Classifier: Programming Language :: Python :: 3.13
Classifier: Topic :: Scientific/Engineering :: Bio-Informatics
Classifier: Topic :: Scientific/Engineering :: Visualization
Requires-Python: >=3.11
License-File: LICENSE.md
Requires-Dist: anndata
Requires-Dist: apted
Requires-Dist: biopython
Requires-Dist: click
Requires-Dist: cython
Requires-Dist: cyvcf2
Requires-Dist: ete3
Requires-Dist: graphviz
Requires-Dist: ipython
Requires-Dist: joblib
Requires-Dist: matplotlib
Requires-Dist: natsort
Requires-Dist: networkx
Requires-Dist: numba
Requires-Dist: numpy
Requires-Dist: pandas
Requires-Dist: pybnb
Requires-Dist: pydot<2.0.0
Requires-Dist: python_sat
Requires-Dist: pyyaml
Requires-Dist: scikit_learn
Requires-Dist: scipy
Requires-Dist: setuptools
Requires-Dist: seaborn
Requires-Dist: termcolor
Requires-Dist: tqdm
Provides-Extra: dev
Requires-Dist: pre-commit; extra == "dev"
Requires-Dist: pytest-cov; extra == "dev"
Requires-Dist: pytest-xdist; extra == "dev"
Requires-Dist: bumpversion; extra == "dev"
Provides-Extra: docs
Requires-Dist: furo; extra == "docs"
Requires-Dist: ipython; extra == "docs"
Requires-Dist: memory_profiler; extra == "docs"
Requires-Dist: nbsphinx; extra == "docs"
Requires-Dist: nbsphinx-link; extra == "docs"
Requires-Dist: pydata_sphinx_theme; extra == "docs"
Requires-Dist: pyenchant; extra == "docs"
Requires-Dist: pypandoc; extra == "docs"
Requires-Dist: sphinx<6; extra == "docs"
Requires-Dist: sphinx-autodoc-typehints; extra == "docs"
Requires-Dist: sphinx-click; extra == "docs"
Requires-Dist: sphinx-paramlinks; extra == "docs"
Requires-Dist: sphinx_copybutton; extra == "docs"
Requires-Dist: sphinx_gallery; extra == "docs"
Requires-Dist: sphinx_rtd_theme; extra == "docs"
Requires-Dist: sphinxcontrib-bibtex; extra == "docs"
Requires-Dist: typing_extensions; extra == "docs"
Dynamic: license-file
